efr/__init__.py
efr/core/__init__.py
efr/core/ealloter.py
efr/core/eerrors.py
efr/core/eframework.py
efr/core/equeue.py
efr/core/estation.py
efr/core/event.py
efr/examples/__init__.py
efr/examples/example2_calc/__init__.py
efr/examples/example2_calc/example_2.py
efr/examples/example3_except/__init__.py
efr/examples/example3_except/example_3.py
efr/examples/exapme1_add/__init__.py
efr/examples/exapme1_add/example_1.py
efr/utils/Functions.py
efr/utils/IdGenerator.py
efr/utils/Task.py
efr/utils/Trace.py
efr/utils/Worker.py
efr/utils/__init__.py
efr-0.2.0.6.dist-info/METADATA
efr-0.2.0.6.dist-info/WHEEL
efr-0.2.0.6.dist-info/top_level.txt
efr-0.2.0.6.dist-info/RECORD
