Metadata-Version: 2.1
Name: efr
Version: 0.2.0.6
Summary: Event-Driver (Stand-alone) Framework. Pure python. Efficient.
Home-page: UNKNOWN
Author: Eagle'sBaby
Author-email: 2229066748@qq.com
Maintainer: Eagle'sBaby
Maintainer-email: 2229066748@qq.com
License: Apache Licence 2.0
Keywords: event-drive
Platform: all
Classifier: Programming Language :: Python
Classifier: Programming Language :: Python :: 3
Requires-Python: >=3
